nlpgraph/__init__.py
nlpgraph/knowledge.py
nlpgraph-0.1.0.dist-info/METADATA
nlpgraph-0.1.0.dist-info/WHEEL
nlpgraph-0.1.0.dist-info/RECORD
